omnicite/__init__.py
omnicite/cli.py
omnicite/core.py
omnicite/exceptions.py
omnicite/pipeline.py
omnicite/templates/conference_paper.yaml
omnicite/templates/journal_article_full.yaml
omnicite-0.0.1.dist-info/licenses/LICENSE
omnicite-0.0.1.dist-info/METADATA
omnicite-0.0.1.dist-info/WHEEL
omnicite-0.0.1.dist-info/entry_points.txt
omnicite-0.0.1.dist-info/top_level.txt
omnicite-0.0.1.dist-info/RECORD
