Metadata-Version: 2.4
Name: omnicite
Version: 0.0.1
Summary: Universal citation management and academic reference toolkit
Home-page: https://github.com/omnicite/omnicite
Author: OmniCite Team
Author-email: OmniCite Team <team@omnicite.org>
License: MIT
Project-URL: Homepage, https://github.com/omnicite/omnicite
Project-URL: Documentation, https://omnicite.readthedocs.io
Project-URL: Repository, https://github.com/omnicite/omnicite
Project-URL: Bug Tracker, https://github.com/omnicite/omnicite/issues
Classifier: Development Status :: 3 - Alpha
Classifier: Intended Audience :: Developers
Classifier: Intended Audience :: Science/Research
Classifier: License :: OSI Approved :: MIT License
Classifier: Operating System :: OS Independent
Classifier: Programming Language :: Python :: 3
Classifier: Programming Language :: Python :: 3.7
Classifier: Programming Language :: Python :: 3.8
Classifier: Programming Language :: Python :: 3.9
Classifier: Programming Language :: Python :: 3.10
Classifier: Programming Language :: Python :: 3.11
Classifier: Programming Language :: Python :: 3.12
Classifier: Topic :: Scientific/Engineering
Classifier: Topic :: Documentation
Classifier: Topic :: Text Processing
Requires-Python: >=3.7
License-File: LICENSE
Requires-Dist: requests>=2.25.0
Requires-Dist: beautifulsoup4>=4.9.0
Requires-Dist: lxml>=4.6.0
Requires-Dist: bibtexparser>=1.4.0
Requires-Dist: PyYAML>=6.0
Requires-Dist: thefuzz>=0.19.0
Requires-Dist: python-Levenshtein>=0.12.0
Requires-Dist: scholarly>=1.7.0
Provides-Extra: dev
Requires-Dist: pytest>=6.0; extra == "dev"
Requires-Dist: black>=21.0; extra == "dev"
Requires-Dist: flake8>=3.8.0; extra == "dev"
Dynamic: author
Dynamic: home-page
Dynamic: license-file
Dynamic: requires-python
